tron_address_converter/__init__.py
tron_address_converter/convert.py
tron_address_converter-1.0.dist-info/LICENSE
tron_address_converter-1.0.dist-info/METADATA
tron_address_converter-1.0.dist-info/WHEEL
tron_address_converter-1.0.dist-info/top_level.txt
tron_address_converter-1.0.dist-info/RECORD
